is_prime/__init__.py
is_prime/prime_checker.py
is_prime_check-1.0.1.dist-info/licenses/LICENSE
is_prime_check-1.0.1.dist-info/METADATA
is_prime_check-1.0.1.dist-info/WHEEL
is_prime_check-1.0.1.dist-info/top_level.txt
is_prime_check-1.0.1.dist-info/RECORD
