Metadata-Version: 2.4
Name: is_prime_check
Version: 1.0.1
Summary: A simple package to check if a number is prime
Home-page: https://github.com/imsomdev/is_prime
Author: Somdev Das
Author-email: somdev4g@gmail.com
Classifier: Programming Language :: Python :: 3
Classifier: License :: OSI Approved :: MIT License
Classifier: Operating System :: OS Independent
Requires-Python: >=3.6
License-File: LICENSE
Dynamic: author
Dynamic: author-email
Dynamic: classifier
Dynamic: description
Dynamic: description-content-type
Dynamic: home-page
Dynamic: license-file
Dynamic: requires-python
Dynamic: summary
